{
  "_postman_id": "jira-mock-v2-env-2025",
  "name": "Jira Mock – Local",
  "values": [
    {
      "key": "base_url",
      "value": "http://localhost:4001",
      "type": "default",
      "enabled": true,
      "description": "Base URL of the running Jira Mock service"
    },
    {
      "key": "api_token",
      "value": "mock-jira-token-2025",
      "type": "secret",
      "enabled": true,
      "description": "Fixed Bearer token. Only this value is accepted by the mock. Used as: Authorization: Bearer mock-jira-token-2025"
    },
    {
      "key": "issue_key",
      "value": "QA-1",
      "type": "default",
      "enabled": true,
      "description": "Issue key used in Read / Edit / Delete / Transition requests. Auto-updated when you run Create Story or Create Bug."
    },
    {
      "key": "created_story_key",
      "value": "",
      "type": "default",
      "enabled": true,
      "description": "Auto-populated by the Create Story request test script."
    },
    {
      "key": "created_bug_key",
      "value": "",
      "type": "default",
      "enabled": true,
      "description": "Auto-populated by the Create Bug request test script."
    },
    {
      "key": "transition_id",
      "value": "2",
      "type": "default",
      "enabled": true,
      "description": "Auto-populated by Get Transitions. Values: 1=To Do, 2=In Progress, 3=Done"
    }
  ],
  "_postman_variable_scope": "environment",
  "_postman_exported_at": "2026-03-23T00:00:00.000Z",
  "_postman_exported_using": "Postman/11.0.0"
}
